drf_jsonapi-0.1.6.dist-info/DESCRIPTION.rst
drf_jsonapi-0.1.6.dist-info/METADATA
drf_jsonapi-0.1.6.dist-info/metadata.json
drf_jsonapi-0.1.6.dist-info/pbr.json
drf_jsonapi-0.1.6.dist-info/RECORD
drf_jsonapi-0.1.6.dist-info/top_level.txt
drf_jsonapi-0.1.6.dist-info/WHEEL
rest_framework_jsonapi/__init__.py
rest_framework_jsonapi/pagination.py
rest_framework_jsonapi/parsers.py
rest_framework_jsonapi/renderers.py
rest_framework_jsonapi/utils.py
rest_framework_jsonapi/views.py
