Metadata-Version: 2.0
Name: drf-jsonapi
Version: 0.1.6
Summary: Django Rest Framework tools which are compliant with the JSONAPI 1.0 specification
Home-page: https://github.com/Naeka/django-rest-framework-jsonapi
Author: Naeka
Author-email: contact@naeka.fr
License: BSD
Platform: UNKNOWN
Classifier: Development Status :: 4 - Beta
Classifier: Environment :: Web Environment
Classifier: Framework :: Django
Classifier: Intended Audience :: Developers
Classifier: License :: OSI Approved :: BSD License
Classifier: Operating System :: OS Independent
Classifier: Natural Language :: English
Classifier: Programming Language :: Python :: 2
Classifier: Programming Language :: Python :: 2.7
Classifier: Programming Language :: Python :: 3
Classifier: Programming Language :: Python :: 3.4
Classifier: Topic :: Internet :: WWW/HTTP
Requires-Dist: inflection (>=0.3.1)
Requires-Dist: djangorestframework (>=3.1,<3.4)
